.gitignore
LICENSE
MANIFEST.in
README.ipynb
README.md
requirements.txt
setup.py
tox.ini
README_files/README_10_0.svg
README_files/README_11_0.png
README_files/README_17_0.svg
cadence/__init__.py
cadence/cadence.py
cadence/imports.py
cadence/constraints/__init__.py
cadence/constraints/constraints.py
cadence/langs/__init__.py
cadence/langs/english.py
cadence/langs/langs.py
cadence/langs/lexconvert.py
cadence/parsers/__init__.py
cadence/parsers/docs.py
cadence/parsers/metrics.py
cadence/parsers/stanzanlp.py
cadence/parsers/txtparsing.py
cadence/parsers/mtree/README.md
cadence/parsers/mtree/__init__.py
cadence/parsers/mtree/deptree.py
cadence/parsers/mtree/get-deps.sh
cadence/parsers/mtree/metricaltree.py
cadence/parsers/mtree/mtree.py
cadence/parsers/mtree/test.py
cadence/tools/__init__.py
cadence/tools/latuni.py
cadence/tools/tools.py
cadences.egg-info/PKG-INFO
cadences.egg-info/SOURCES.txt
cadences.egg-info/dependency_links.txt
cadences.egg-info/requires.txt
cadences.egg-info/top_level.txt
data/data.feats.ipa.csv
data/en/cmudict.txt
data/en/maybestressed.txt
data/en/unstressed.txt
notebooks/cadence_docobjs.ipynb
notebooks/cadence_mtree.ipynb
notebooks/cadence_parser.ipynb
notebooks/cadence_proms.ipynb
notebooks/cadence_stanza.ipynb
notebooks/engines.ipynb
notebooks/example_sonnets.ipynb
notebooks/lineation.ipynb
notebooks/newtextobjs.ipynb
notebooks/pmap.ipynb
notebooks/test-bounding.ipynb
notebooks/test_cleanup.ipynb
notebooks/test_db.ipynb
notebooks/test_grid.ipynb
notebooks/test_objs.ipynb
notebooks/test_parse_display.ipynb
notebooks/test_parsing.ipynb
notebooks/test_scansion.ipynb
notebooks/test_sent_trees.ipynb
notebooks/test_tokenizer.ipynb
notebooks/test_weight.ipynb
notebooks/webapp.ipynb
tests/test_sample.py